{"mc":{"110625":{"frameRate":14,"frames":[{"res":"1106250","x":-40,"y":-109},{"res":"1106251","x":-41,"y":-111},{"res":"1106252","x":-42,"y":-110},{"res":"1106253","x":-46,"y":-108},{"res":"1106254","x":-41,"y":-110},{"res":"1106255","x":-41,"y":-109}]}},"res":{"1106250":{"x":169,"y":234,"w":84,"h":112},"1106251":{"x":1,"y":1,"w":82,"h":123},"1106252":{"x":85,"y":124,"w":82,"h":115},"1106253":{"x":169,"y":121,"w":85,"h":111},"1106254":{"x":85,"y":1,"w":82,"h":121},"1106255":{"x":169,"y":1,"w":81,"h":118}}}