{"mc":{"330923":{"frameRate":14,"frames":[{"res":"3309230","x":-80,"y":-76},{"res":"3309231","x":-93,"y":-62},{"res":"3309232","x":-84,"y":-63},{"res":"3309233","x":-56,"y":-84},{"res":"3309234","x":-42,"y":-95},{"res":"3309235","x":-50,"y":-87}]}},"res":{"3309230":{"x":257,"y":90,"w":150,"h":70},"3309231":{"x":1,"y":157,"w":159,"h":43},"3309232":{"x":1,"y":104,"w":158,"h":51},"3309233":{"x":257,"y":1,"w":139,"h":87},"3309234":{"x":1,"y":1,"w":124,"h":101},"3309235":{"x":127,"y":1,"w":128,"h":96}}}