{"mc":{"140434":{"frameRate":14,"frames":[{"res":"1404340","x":-85,"y":-95},{"res":"1404341","x":-83,"y":-101},{"res":"1404342","x":-62,"y":-116},{"res":"1404343","x":-56,"y":-89},{"res":"1404344","x":-64,"y":-101},{"res":"1404345","x":-77,"y":-88}]}},"res":{"1404340":{"x":239,"y":1,"w":123,"h":101},"1404341":{"x":1,"y":1,"w":125,"h":105},"1404342":{"x":128,"y":1,"w":109,"h":120},"1404343":{"x":1,"y":108,"w":102,"h":93},"1404344":{"x":364,"y":1,"w":115,"h":105},"1404345":{"x":239,"y":104,"w":114,"h":92}}}