{"mc":{"120525":{"frameRate":14,"frames":[{"res":"1205250","x":-59,"y":-107},{"res":"1205251","x":-29,"y":-107},{"res":"1205252","x":-24,"y":-105},{"res":"1205253","x":-46,"y":-107},{"res":"1205254","x":-56,"y":-108},{"res":"1205255","x":-48,"y":-106}]}},"res":{"1205250":{"x":92,"y":1,"w":88,"h":119},"1205251":{"x":1,"y":124,"w":57,"h":120},"1205252":{"x":182,"y":1,"w":53,"h":119},"1205253":{"x":92,"y":122,"w":81,"h":121},"1205254":{"x":1,"y":1,"w":89,"h":121},"1205255":{"x":175,"y":122,"w":77,"h":120}}}