{"mc":{"110232":{"frameRate":14,"frames":[{"res":"1102320","x":-32,"y":-89},{"res":"1102321","x":-36,"y":-77},{"res":"1102322","x":-21,"y":-98},{"res":"1102323","x":-27,"y":-116},{"res":"1102324","x":-25,"y":-102},{"res":"1102325","x":-27,"y":-100}]}},"res":{"1102320":{"x":142,"y":124,"w":55,"h":108},"1102321":{"x":1,"y":138,"w":61,"h":96},"1102322":{"x":82,"y":122,"w":58,"h":117},"1102323":{"x":1,"y":1,"w":79,"h":135},"1102324":{"x":155,"y":1,"w":67,"h":121},"1102325":{"x":82,"y":1,"w":71,"h":119}}}