{"mc":{"211821":{"frameRate":14,"frames":[{"res":"2118210","x":-41,"y":-106},{"res":"2118211","x":-41,"y":-105},{"res":"2118212","x":-39,"y":-107},{"res":"2118213","x":-36,"y":-106},{"res":"2118214","x":-35,"y":-106},{"res":"2118215","x":-39,"y":-107}]}},"res":{"2118210":{"x":92,"y":131,"w":84,"h":128},"2118211":{"x":93,"y":1,"w":85,"h":128},"2118212":{"x":1,"y":247,"w":87,"h":123},"2118213":{"x":1,"y":1,"w":90,"h":121},"2118214":{"x":90,"y":261,"w":89,"h":116},"2118215":{"x":1,"y":124,"w":89,"h":121}}}