{"mc":{"110142":{"frameRate":14,"frames":[{"res":"1101420","x":-16,"y":-96},{"res":"1101421","x":-17,"y":-94},{"res":"1101422","x":-18,"y":-92},{"res":"1101423","x":-24,"y":-108},{"res":"1101424","x":-27,"y":-111},{"res":"1101425","x":-25,"y":-96}]}},"res":{"1101420":{"x":160,"y":1,"w":45,"h":117},"1101421":{"x":207,"y":116,"w":37,"h":115},"1101422":{"x":207,"y":1,"w":41,"h":113},"1101423":{"x":111,"y":1,"w":47,"h":129},"1101424":{"x":61,"y":1,"w":48,"h":132},"1101425":{"x":1,"y":1,"w":58,"h":117}}}