{"mc":{"170023":{"frameRate":14,"frames":[{"res":"1700230","x":-38,"y":-105},{"res":"1700231","x":-49,"y":-105},{"res":"1700232","x":-37,"y":-103},{"res":"1700233","x":-35,"y":-105},{"res":"1700234","x":-48,"y":-105},{"res":"1700235","x":-36,"y":-103}]}},"res":{"1700230":{"x":183,"y":1,"w":70,"h":103},"1700231":{"x":1,"y":1,"w":90,"h":102},"1700232":{"x":1,"y":105,"w":63,"h":107},"1700233":{"x":93,"y":97,"w":64,"h":106},"1700234":{"x":93,"y":1,"w":88,"h":94},"1700235":{"x":159,"y":106,"w":59,"h":101}}}