{"mc":{"eff70205":{"frameRate":14,"frames":[{"res":"eff702050","x":-180,"y":-180},{"res":"eff702051","x":-124,"y":-111},{"res":"eff702052","x":-166,"y":-89},{"res":"eff702053","x":-172,"y":-83},{"res":"eff702054","x":-174,"y":-91},{"res":"eff702055","x":-173,"y":-92}]}},"res":{"eff702050":{"x":942,"y":1,"w":5,"h":5},"eff702051":{"x":1,"y":1,"w":296,"h":203},"eff702052":{"x":299,"y":1,"w":324,"h":182},"eff702053":{"x":615,"y":186,"w":318,"h":176},"eff702054":{"x":625,"y":1,"w":315,"h":183},"eff702055":{"x":299,"y":185,"w":314,"h":183}}}