{"mc":{"eff70201":{"frameRate":14,"frames":[{"res":"eff702010","x":-256,"y":-256},{"res":"eff702011","x":-38,"y":-93},{"res":"eff702012","x":-57,"y":-111},{"res":"eff702013","x":-157,"y":-188},{"res":"eff702014","x":-157,"y":-191},{"res":"eff702015","x":-158,"y":-189},{"res":"eff702016","x":-149,"y":-191},{"res":"eff702017","x":-149,"y":-187},{"res":"eff702018","x":-155,"y":-183},{"res":"eff702019","x":-100,"y":-181}]}},"res":{"eff702010":{"x":1004,"y":1,"w":5,"h":5},"eff702011":{"x":1,"y":477,"w":77,"h":118},"eff702012":{"x":561,"y":468,"w":113,"h":155},"eff702013":{"x":1,"y":241,"w":320,"h":234},"eff702014":{"x":681,"y":239,"w":320,"h":239},"eff702015":{"x":673,"y":1,"w":329,"h":236},"eff702016":{"x":1,"y":1,"w":334,"h":238},"eff702017":{"x":337,"y":1,"w":334,"h":234},"eff702018":{"x":337,"y":239,"w":342,"h":227},"eff702019":{"x":323,"y":468,"w":236,"h":220}}}