{"mc":{"efficon":{"frameRate":14,"frames":[{"res":"efficon0","x":-41,"y":-42},{"res":"efficon1","x":-41,"y":-42},{"res":"efficon2","x":-41,"y":-42},{"res":"efficon3","x":-41,"y":-42},{"res":"efficon4","x":-41,"y":-42},{"res":"efficon5","x":-41,"y":-42}]}},"res":{"efficon0":{"x":1,"y":85,"w":82,"h":82},"efficon1":{"x":86,"y":1,"w":82,"h":82},"efficon2":{"x":170,"y":1,"w":82,"h":82},"efficon3":{"x":1,"y":1,"w":83,"h":82},"efficon4":{"x":85,"y":85,"w":82,"h":82},"efficon5":{"x":169,"y":85,"w":82,"h":82}}}