{"mc":{"efftld":{"frameRate":14,"frames":[{"res":"efftld0","x":-150,"y":-156},{"res":"efftld1","x":-151,"y":-156},{"res":"efftld2","x":-147,"y":-151},{"res":"efftld3","x":-146,"y":-154},{"res":"efftld4","x":-148,"y":-166},{"res":"efftld5","x":-148,"y":-168}]}},"res":{"efftld0":{"x":1,"y":261,"w":287,"h":242},"efftld1":{"x":611,"y":250,"w":290,"h":244},"efftld2":{"x":290,"y":262,"w":288,"h":241},"efftld3":{"x":611,"y":1,"w":291,"h":247},"efftld4":{"x":307,"y":1,"w":302,"h":259},"efftld5":{"x":1,"y":1,"w":304,"h":258}}}