{"mc":{"sxcg":{"frameRate":14,"frames":[{"res":"sxcg0","x":-360,"y":-568},{"res":"sxcg1","x":-311,"y":-158},{"res":"sxcg10","x":-333,"y":-221},{"res":"sxcg2","x":-308,"y":-156},{"res":"sxcg3","x":-306,"y":-165},{"res":"sxcg4","x":-308,"y":-189},{"res":"sxcg5","x":-306,"y":-185},{"res":"sxcg6","x":-299,"y":-187},{"res":"sxcg7","x":-306,"y":-181},{"res":"sxcg8","x":-309,"y":-167},{"res":"sxcg9","x":-324,"y":-221}]}},"res":{"sxcg0":{"x":1847,"y":1,"w":5,"h":5},"sxcg1":{"x":1227,"y":1,"w":618,"h":315},"sxcg10":{"x":1238,"y":939,"w":613,"h":302},"sxcg2":{"x":624,"y":630,"w":612,"h":310},"sxcg3":{"x":1,"y":661,"w":609,"h":306},"sxcg4":{"x":1227,"y":318,"w":618,"h":310},"sxcg5":{"x":1,"y":1,"w":613,"h":348},"sxcg6":{"x":616,"y":1,"w":609,"h":323},"sxcg7":{"x":1238,"y":630,"w":609,"h":307},"sxcg8":{"x":1,"y":351,"w":621,"h":308},"sxcg9":{"x":612,"y":942,"w":602,"h":302}}}